[{"line":1,"elements":[{"start_timestamp":"2022-09-04T09:23:30.287Z","line":10,"name":"Verifying Adactin login with valid credentials","description":"","id":"verifying-adactin-login-hotel-details;verifying-adactin-login-with-valid-credentials;;2","type":"scenario","keyword":"Scenario Outline","steps":[{"result":{"duration":10943000000,"status":"passed"},"line":4,"name":"User is on the adactin page","match":{"location":"org.stepdefinition.TC1_LoginStep.userIsOnTheAdactinPage()"},"keyword":"Given "},{"result":{"duration":3488000000,"status":"passed"},"line":5,"name":"User should perform login \"Sivasankaran\" and \"Siva1983\"","match":{"arguments":[{"val":"\"Sivasankaran\"","offset":26},{"val":"\"Siva1983\"","offset":45}],"location":"org.stepdefinition.TC1_LoginStep.userShouldPerformLoginAnd(java.lang.String,java.lang.String)"},"keyword":"When "},{"result":{"duration":2000000,"status":"passed"},"line":6,"name":"User should verify success msg after login \"Hello Sivasankaran!\"","match":{"arguments":[{"val":"\"Hello Sivasankaran!\"","offset":43}],"location":"org.stepdefinition.TC1_LoginStep.userShouldVerifySuccessMsgAfterLogin(java.lang.String)"},"keyword":"Then "}]},{"start_timestamp":"2022-09-04T09:23:45.066Z","line":19,"name":"Verifying Adactin login with valid credentials with Enter","description":"","id":"verifying-adactin-login-hotel-details;verifying-adactin-login-with-valid-credentials-with-enter;;2","type":"scenario","keyword":"Scenario Outline","steps":[{"result":{"duration":7878000000,"status":"passed"},"line":13,"name":"User is on the adactin page","match":{"location":"org.stepdefinition.TC1_LoginStep.userIsOnTheAdactinPage()"},"keyword":"Given "},{"result":{"status":"undefined"},"line":14,"name":"User should perform login \"Sivasankaran\", \"Siva1983\" with Enter key","match":{},"keyword":"When "},{"result":{"duration":2000000,"status":"skipped"},"line":15,"name":"User should verify success msg after login \"Hello Sivasankaran!\"","match":{"arguments":[{"val":"\"Hello Sivasankaran!\"","offset":43}],"location":"org.stepdefinition.TC1_LoginStep.userShouldVerifySuccessMsgAfterLogin(java.lang.String)"},"keyword":"Then "}]}],"name":"Verifying Adactin Login Hotel details","description":"","id":"verifying-adactin-login-hotel-details","keyword":"Feature","uri":"file:src/test/resources/Features/TC1_Login.feature","tags":[]}]